jupybeans.py
jupybeans-0.1.0.dist-info/WHEEL
jupybeans-0.1.0.dist-info/METADATA
jupybeans-0.1.0.dist-info/RECORD
