Metadata-Version: 2.1
Name: jupybeans
Version: 0.1.0
Summary: 
Author: Gordon Bean
Author-email: gbean@cs.byu.edu
Requires-Python: >=3.8,<4.0
Classifier: Programming Language :: Python :: 3
Classifier: Programming Language :: Python :: 3.10
Classifier: Programming Language :: Python :: 3.8
Classifier: Programming Language :: Python :: 3.9
Requires-Dist: jupyter (>=1.0.0,<2.0.0)
